{
  "type": "minecraft:crafting_shaped",
  "category": "equipment",
  "key": {
    "#": {
      "item": "dreamcraftmod:echo_block"
    },
    "D": {
      "item": "minecraft:blaze_rod"
    },
    "G": {
      "item": "dreamcraftmod:shaft"
    },
    "S": {
      "item": "minecraft:netherite_ingot"
    },
    "Z": {
      "item": "minecraft:gold_block"
    }
  },
  "pattern": [
    "ZS#",
    " D#",
    "G  "
  ],
  "result": {
    "item": "dreamcraftmod:echo_axe"
  },
  "show_notification": true
}